{
  "cookies": [],
  "origins": [
    {
      "origin": "https://admin.testing.evergreenseamless.com",
      "localStorage": [
        {
          "name": "versionUpdateNow",
          "value": "false"
        },
        {
          "name": "isLoggedIn",
          "value": "true"
        },
        {
          "name": "token",
          "value": "eyJhbGciOiJIUzI1NiIsInR5cCI6IkpXVCJ9.eyJ1c2VySWQiOjI0NiwidXNlcm5hbWUiOiJHcmVlbiBBcnJvdyIsImlhdCI6MTc0ODU5NDY2MCwiZXhwIjoxNzQ5ODU5MjAwfQ.APKrpvGkChBWtx9gpYxbH-BSLG9gL8O-oEXPVsGKCTY"
        },
        {
          "name": "user",
          "value": "{\"id\":246,\"is_commission_agent\":false,\"commission_agents\":[],\"first_name\":\"Green\",\"last_name\":\"Arrow\",\"email\":\"rohan+green@alchemytech.ca\",\"type\":\"PERMANENT\",\"is_first_login\":false,\"branch\":{\"id\":3,\"name\":\"BANGALORE\"},\"permission\":[{\"id\":1,\"name\":\"List\",\"slug\":\"list\",\"module\":{\"id\":1,\"name\":\"Department\",\"slug\":\"department\"}},{\"id\":3,\"name\":\"Add\",\"slug\":\"add\",\"module\":{\"id\":1,\"name\":\"Department\",\"slug\":\"department\"}},{\"id\":4,\"name\":\"Update\",\"slug\":\"update\",\"module\":{\"id\":1,\"name\":\"Department\",\"slug\":\"department\"}},{\"id\":5,\"name\":\"Delete\",\"slug\":\"delete\",\"module\":{\"id\":1,\"name\":\"Department\",\"slug\":\"department\"}},{\"id\":6,\"name\":\"List\",\"slug\":\"list\",\"module\":{\"id\":2,\"name\":\"Designation\",\"slug\":\"designation\"}},{\"id\":7,\"name\":\"Add\",\"slug\":\"add\",\"module\":{\"id\":2,\"name\":\"Designation\",\"slug\":\"designation\"}},{\"id\":8,\"name\":\"Update\",\"slug\":\"update\",\"module\":{\"id\":2,\"name\":\"Designation\",\"slug\":\"designation\"}},{\"id\":9,\"name\":\"Delete\",\"slug\":\"delete\",\"module\":{\"id\":2,\"name\":\"Designation\",\"slug\":\"designation\"}},{\"id\":10,\"name\":\"List\",\"slug\":\"list\",\"module\":{\"id\":3,\"name\":\"User\",\"slug\":\"user\"}},{\"id\":11,\"name\":\"Add\",\"slug\":\"add\",\"module\":{\"id\":3,\"name\":\"User\",\"slug\":\"user\"}},{\"id\":12,\"name\":\"Update\",\"slug\":\"update\",\"module\":{\"id\":3,\"name\":\"User\",\"slug\":\"user\"}},{\"id\":13,\"name\":\"Delete\",\"slug\":\"delete\",\"module\":{\"id\":3,\"name\":\"User\",\"slug\":\"user\"}},{\"id\":14,\"name\":\"List\",\"slug\":\"list\",\"module\":{\"id\":4,\"name\":\"Group\",\"slug\":\"group\"}},{\"id\":15,\"name\":\"Add\",\"slug\":\"add\",\"module\":{\"id\":4,\"name\":\"Group\",\"slug\":\"group\"}},{\"id\":16,\"name\":\"Update\",\"slug\":\"update\",\"module\":{\"id\":4,\"name\":\"Group\",\"slug\":\"group\"}},{\"id\":17,\"name\":\"Delete\",\"slug\":\"delete\",\"module\":{\"id\":4,\"name\":\"Group\",\"slug\":\"group\"}},{\"id\":18,\"name\":\"List\",\"slug\":\"list\",\"module\":{\"id\":5,\"name\":\"Employee\",\"slug\":\"employee\"}},{\"id\":19,\"name\":\"Add\",\"slug\":\"add\",\"module\":{\"id\":5,\"name\":\"Employee\",\"slug\":\"employee\"}},{\"id\":20,\"name\":\"Update\",\"slug\":\"update\",\"module\":{\"id\":5,\"name\":\"Employee\",\"slug\":\"employee\"}},{\"id\":21,\"name\":\"Delete\",\"slug\":\"delete\",\"module\":{\"id\":5,\"name\":\"Employee\",\"slug\":\"employee\"}},{\"id\":22,\"name\":\"List\",\"slug\":\"list\",\"module\":{\"id\":6,\"name\":\"Customer\",\"slug\":\"customer\"}},{\"id\":23,\"name\":\"Add\",\"slug\":\"add\",\"module\":{\"id\":6,\"name\":\"Customer\",\"slug\":\"customer\"}},{\"id\":24,\"name\":\"Update\",\"slug\":\"update\",\"module\":{\"id\":6,\"name\":\"Customer\",\"slug\":\"customer\"}},{\"id\":25,\"name\":\"Delete\",\"slug\":\"delete\",\"module\":{\"id\":6,\"name\":\"Customer\",\"slug\":\"customer\"}},{\"id\":26,\"name\":\"List\",\"slug\":\"list\",\"module\":{\"id\":7,\"name\":\"PaymentTerms\",\"slug\":\"paymentterms\"}},{\"id\":27,\"name\":\"Add\",\"slug\":\"add\",\"module\":{\"id\":7,\"name\":\"PaymentTerms\",\"slug\":\"paymentterms\"}},{\"id\":28,\"name\":\"Update\",\"slug\":\"update\",\"module\":{\"id\":7,\"name\":\"PaymentTerms\",\"slug\":\"paymentterms\"}},{\"id\":29,\"name\":\"Delete\",\"slug\":\"delete\",\"module\":{\"id\":7,\"name\":\"PaymentTerms\",\"slug\":\"paymentterms\"}},{\"id\":30,\"name\":\"List\",\"slug\":\"list\",\"module\":{\"id\":8,\"name\":\"DeliveryConditions\",\"slug\":\"deliveryconditions\"}},{\"id\":31,\"name\":\"Add\",\"slug\":\"add\",\"module\":{\"id\":8,\"name\":\"DeliveryConditions\",\"slug\":\"deliveryconditions\"}},{\"id\":32,\"name\":\"Update\",\"slug\":\"update\",\"module\":{\"id\":8,\"name\":\"DeliveryConditions\",\"slug\":\"deliveryconditions\"}},{\"id\":33,\"name\":\"Delete\",\"slug\":\"delete\",\"module\":{\"id\":8,\"name\":\"DeliveryConditions\",\"slug\":\"deliveryconditions\"}},{\"id\":34,\"name\":\"List\",\"slug\":\"list\",\"module\":{\"id\":9,\"name\":\"DeliveryLocations\",\"slug\":\"deliverylocations\"}},{\"id\":35,\"name\":\"Add\",\"slug\":\"add\",\"module\":{\"id\":9,\"name\":\"DeliveryLocations\",\"slug\":\"deliverylocations\"}},{\"id\":36,\"name\":\"Update\",\"slug\":\"update\",\"module\":{\"id\":9,\"name\":\"DeliveryLocations\",\"slug\":\"deliverylocations\"}},{\"id\":37,\"name\":\"Delete\",\"slug\":\"delete\",\"module\":{\"id\":9,\"name\":\"DeliveryLocations\",\"slug\":\"deliverylocations\"}},{\"id\":38,\"name\":\"List\",\"slug\":\"list\",\"module\":{\"id\":10,\"name\":\"SupplierType\",\"slug\":\"suppliertypes\"}},{\"id\":39,\"name\":\"Add\",\"slug\":\"add\",\"module\":{\"id\":10,\"name\":\"SupplierType\",\"slug\":\"suppliertypes\"}},{\"id\":40,\"name\":\"Update\",\"slug\":\"update\",\"module\":{\"id\":10,\"name\":\"SupplierType\",\"slug\":\"suppliertypes\"}},{\"id\":41,\"name\":\"Delete\",\"slug\":\"delete\",\"module\":{\"id\":10,\"name\":\"SupplierType\",\"slug\":\"suppliertypes\"}},{\"id\":42,\"name\":\"List\",\"slug\":\"list\",\"module\":{\"id\":11,\"name\":\"Sector\",\"slug\":\"sector\"}},{\"id\":43,\"name\":\"Add\",\"slug\":\"add\",\"module\":{\"id\":11,\"name\":\"Sector\",\"slug\":\"sector\"}},{\"id\":44,\"name\":\"Update\",\"slug\":\"update\",\"module\":{\"id\":11,\"name\":\"Sector\",\"slug\":\"sector\"}},{\"id\":45,\"name\":\"Delete\",\"slug\":\"delete\",\"module\":{\"id\":11,\"name\":\"Sector\",\"slug\":\"sector\"}},{\"id\":46,\"name\":\"List\",\"slug\":\"list\",\"module\":{\"id\":12,\"name\":\"Bank\",\"slug\":\"bank\"}},{\"id\":47,\"name\":\"Add\",\"slug\":\"add\",\"module\":{\"id\":12,\"name\":\"Bank\",\"slug\":\"bank\"}},{\"id\":48,\"name\":\"Update\",\"slug\":\"update\",\"module\":{\"id\":12,\"name\":\"Bank\",\"slug\":\"bank\"}},{\"id\":49,\"name\":\"Delete\",\"slug\":\"delete\",\"module\":{\"id\":12,\"name\":\"Bank\",\"slug\":\"bank\"}},{\"id\":50,\"name\":\"List\",\"slug\":\"list\",\"module\":{\"id\":13,\"name\":\"Materials\",\"slug\":\"materials\"}},{\"id\":51,\"name\":\"Add\",\"slug\":\"add\",\"module\":{\"id\":13,\"name\":\"Materials\",\"slug\":\"materials\"}},{\"id\":52,\"name\":\"Update\",\"slug\":\"update\",\"module\":{\"id\":13,\"name\":\"Materials\",\"slug\":\"materials\"}},{\"id\":53,\"name\":\"Delete\",\"slug\":\"delete\",\"module\":{\"id\":13,\"name\":\"Materials\",\"slug\":\"materials\"}},{\"id\":54,\"name\":\"List\",\"slug\":\"list\",\"module\":{\"id\":14,\"name\":\"MaterialType\",\"slug\":\"materialtype\"}},{\"id\":55,\"name\":\"Add\",\"slug\":\"add\",\"module\":{\"id\":14,\"name\":\"MaterialType\",\"slug\":\"materialtype\"}},{\"id\":56,\"name\":\"Update\",\"slug\":\"update\",\"module\":{\"id\":14,\"name\":\"MaterialType\",\"slug\":\"materialtype\"}},{\"id\":57,\"name\":\"Delete\",\"slug\":\"delete\",\"module\":{\"id\":14,\"name\":\"MaterialType\",\"slug\":\"materialtype\"}},{\"id\":58,\"name\":\"List\",\"slug\":\"list\",\"module\":{\"id\":15,\"name\":\"MaterialTest\",\"slug\":\"materialtest\"}},{\"id\":59,\"name\":\"Add\",\"slug\":\"add\",\"module\":{\"id\":15,\"name\":\"MaterialTest\",\"slug\":\"materialtest\"}},{\"id\":60,\"name\":\"Update\",\"slug\":\"update\",\"module\":{\"id\":15,\"name\":\"MaterialTest\",\"slug\":\"materialtest\"}},{\"id\":61,\"name\":\"Delete\",\"slug\":\"delete\",\"module\":{\"id\":15,\"name\":\"MaterialTest\",\"slug\":\"materialtest\"}},{\"id\":62,\"name\":\"List\",\"slug\":\"list\",\"module\":{\"id\":16,\"name\":\"MaterialMake\",\"slug\":\"materialnake\"}},{\"id\":63,\"name\":\"Add\",\"slug\":\"add\",\"module\":{\"id\":16,\"name\":\"MaterialMake\",\"slug\":\"materialnake\"}},{\"id\":64,\"name\":\"Update\",\"slug\":\"update\",\"module\":{\"id\":16,\"name\":\"MaterialMake\",\"slug\":\"materialnake\"}},{\"id\":65,\"name\":\"Delete\",\"slug\":\"delete\",\"module\":{\"id\":16,\"name\":\"MaterialMake\",\"slug\":\"materialnake\"}},{\"id\":66,\"name\":\"List\",\"slug\":\"list\",\"module\":{\"id\":17,\"name\":\"PriceBasis\",\"slug\":\"pricebasis\"}},{\"id\":67,\"name\":\"Add\",\"slug\":\"add\",\"module\":{\"id\":17,\"name\":\"PriceBasis\",\"slug\":\"pricebasis\"}},{\"id\":68,\"name\":\"Update\",\"slug\":\"update\",\"module\":{\"id\":17,\"name\":\"PriceBasis\",\"slug\":\"pricebasis\"}},{\"id\":69,\"name\":\"Delete\",\"slug\":\"delete\",\"module\":{\"id\":17,\"name\":\"PriceBasis\",\"slug\":\"pricebasis\"}},{\"id\":70,\"name\":\"List\",\"slug\":\"list\",\"module\":{\"id\":18,\"name\":\"MaterialCategory\",\"slug\":\"materialcategory\"}},{\"id\":71,\"name\":\"Add\",\"slug\":\"add\",\"module\":{\"id\":18,\"name\":\"MaterialCategory\",\"slug\":\"materialcategory\"}},{\"id\":72,\"name\":\"Update\",\"slug\":\"update\",\"module\":{\"id\":18,\"name\":\"MaterialCategory\",\"slug\":\"materialcategory\"}},{\"id\":73,\"name\":\"Delete\",\"slug\":\"delete\",\"module\":{\"id\":18,\"name\":\"MaterialCategory\",\"slug\":\"materialcategory\"}},{\"id\":74,\"name\":\"List\",\"slug\":\"list\",\"module\":{\"id\":19,\"name\":\"TPIAgency\",\"slug\":\"tpiagency\"}},{\"id\":75,\"name\":\"Add\",\"slug\":\"add\",\"module\":{\"id\":19,\"name\":\"TPIAgency\",\"slug\":\"tpiagency\"}},{\"id\":76,\"name\":\"Update\",\"slug\":\"update\",\"module\":{\"id\":19,\"name\":\"TPIAgency\",\"slug\":\"tpiagency\"}},{\"id\":77,\"name\":\"Delete\",\"slug\":\"delete\",\"module\":{\"id\":19,\"name\":\"TPIAgency\",\"slug\":\"tpiagency\"}},{\"id\":82,\"name\":\"List\",\"slug\":\"list\",\"module\":{\"id\":21,\"name\":\"MaterialSpecification\",\"slug\":\"materialspecification\"}},{\"id\":83,\"name\":\"Add\",\"slug\":\"add\",\"module\":{\"id\":21,\"name\":\"MaterialSpecification\",\"slug\":\"materialspecification\"}},{\"id\":84,\"name\":\"Update\",\"slug\":\"update\",\"module\":{\"id\":21,\"name\":\"MaterialSpecification\",\"slug\":\"materialspecification\"}},{\"id\":85,\"name\":\"Delete\",\"slug\":\"delete\",\"module\":{\"id\":21,\"name\":\"MaterialSpecification\",\"slug\":\"materialspecification\"}},{\"id\":86,\"name\":\"List\",\"slug\":\"list\",\"module\":{\"id\":22,\"name\":\"Dimension\",\"slug\":\"dimension\"}},{\"id\":87,\"name\":\"Add\",\"slug\":\"add\",\"module\":{\"id\":22,\"name\":\"Dimension\",\"slug\":\"dimension\"}},{\"id\":88,\"name\":\"Update\",\"slug\":\"update\",\"module\":{\"id\":22,\"name\":\"Dimension\",\"slug\":\"dimension\"}},{\"id\":89,\"name\":\"Delete\",\"slug\":\"delete\",\"module\":{\"id\":22,\"name\":\"Dimension\",\"slug\":\"dimension\"}},{\"id\":90,\"name\":\"List\",\"slug\":\"list\",\"module\":{\"id\":23,\"name\":\"Product\",\"slug\":\"product\"}},{\"id\":91,\"name\":\"Add\",\"slug\":\"add\",\"module\":{\"id\":23,\"name\":\"Product\",\"slug\":\"product\"}},{\"id\":92,\"name\":\"Update\",\"slug\":\"update\",\"module\":{\"id\":23,\"name\":\"Product\",\"slug\":\"product\"}},{\"id\":93,\"name\":\"Delete\",\"slug\":\"delete\",\"module\":{\"id\":23,\"name\":\"Product\",\"slug\":\"product\"}},{\"id\":94,\"name\":\"List\",\"slug\":\"list\",\"module\":{\"id\":24,\"name\":\"BankBranch\",\"slug\":\"bankbranch\"}},{\"id\":95,\"name\":\"Add\",\"slug\":\"add\",\"module\":{\"id\":24,\"name\":\"BankBranch\",\"slug\":\"bankbranch\"}},{\"id\":96,\"name\":\"Update\",\"slug\":\"update\",\"module\":{\"id\":24,\"name\":\"BankBranch\",\"slug\":\"bankbranch\"}},{\"id\":97,\"name\":\"Delete\",\"slug\":\"delete\",\"module\":{\"id\":24,\"name\":\"BankBranch\",\"slug\":\"bankbranch\"}},{\"id\":98,\"name\":\"List\",\"slug\":\"list\",\"module\":{\"id\":25,\"name\":\"TechnicalQuotation\",\"slug\":\"technicalquotation\"}},{\"id\":99,\"name\":\"Add\",\"slug\":\"add\",\"module\":{\"id\":25,\"name\":\"TechnicalQuotation\",\"slug\":\"technicalquotation\"}},{\"id\":100,\"name\":\"Update\",\"slug\":\"update\",\"module\":{\"id\":25,\"name\":\"TechnicalQuotation\",\"slug\":\"technicalquotation\"}},{\"id\":101,\"name\":\"Delete\",\"slug\":\"delete\",\"module\":{\"id\":25,\"name\":\"TechnicalQuotation\",\"slug\":\"technicalquotation\"}},{\"id\":117,\"name\":\"Approve\",\"slug\":\"approve\",\"module\":{\"id\":14,\"name\":\"MaterialType\",\"slug\":\"materialtype\"}},{\"id\":118,\"name\":\"Approve\",\"slug\":\"approve\",\"module\":{\"id\":13,\"name\":\"Materials\",\"slug\":\"materials\"}},{\"id\":119,\"name\":\"Approve\",\"slug\":\"approve\",\"module\":{\"id\":15,\"name\":\"MaterialTest\",\"slug\":\"materialtest\"}},{\"id\":120,\"name\":\"Approve\",\"slug\":\"approve\",\"module\":{\"id\":16,\"name\":\"MaterialMake\",\"slug\":\"materialnake\"}},{\"id\":121,\"name\":\"Approve\",\"slug\":\"approve\",\"module\":{\"id\":23,\"name\":\"Product\",\"slug\":\"product\"}},{\"id\":122,\"name\":\"Approve\",\"slug\":\"approve\",\"module\":{\"id\":21,\"name\":\"MaterialSpecification\",\"slug\":\"materialspecification\"}},{\"id\":123,\"name\":\"Approve\",\"slug\":\"approve\",\"module\":{\"id\":18,\"name\":\"MaterialCategory\",\"slug\":\"materialcategory\"}},{\"id\":124,\"name\":\"List\",\"slug\":\"list\",\"module\":{\"id\":26,\"name\":\"RegretReason\",\"slug\":\"regretreason\"}},{\"id\":125,\"name\":\"Add\",\"slug\":\"add\",\"module\":{\"id\":26,\"name\":\"RegretReason\",\"slug\":\"regretreason\"}},{\"id\":126,\"name\":\"Update\",\"slug\":\"update\",\"module\":{\"id\":26,\"name\":\"RegretReason\",\"slug\":\"regretreason\"}},{\"id\":127,\"name\":\"Delete\",\"slug\":\"delete\",\"module\":{\"id\":26,\"name\":\"RegretReason\",\"slug\":\"regretreason\"}},{\"id\":128,\"name\":\"List\",\"slug\":\"list\",\"module\":{\"id\":27,\"name\":\"Supplier\",\"slug\":\"supplier\"}},{\"id\":129,\"name\":\"Add\",\"slug\":\"add\",\"module\":{\"id\":27,\"name\":\"Supplier\",\"slug\":\"supplier\"}},{\"id\":130,\"name\":\"Update\",\"slug\":\"update\",\"module\":{\"id\":27,\"name\":\"Supplier\",\"slug\":\"supplier\"}},{\"id\":131,\"name\":\"Delete\",\"slug\":\"delete\",\"module\":{\"id\":27,\"name\":\"Supplier\",\"slug\":\"supplier\"}},{\"id\":132,\"name\":\"List\",\"slug\":\"list\",\"module\":{\"id\":28,\"name\":\"Project\",\"slug\":\"project\"}},{\"id\":133,\"name\":\"Add\",\"slug\":\"add\",\"module\":{\"id\":28,\"name\":\"Project\",\"slug\":\"project\"}},{\"id\":134,\"name\":\"Update\",\"slug\":\"update\",\"module\":{\"id\":28,\"name\":\"Project\",\"slug\":\"project\"}},{\"id\":135,\"name\":\"Delete\",\"slug\":\"delete\",\"module\":{\"id\":28,\"name\":\"Project\",\"slug\":\"project\"}},{\"id\":136,\"name\":\"List\",\"slug\":\"list\",\"module\":{\"id\":29,\"name\":\"ITP\",\"slug\":\"itp\"}},{\"id\":137,\"name\":\"Add\",\"slug\":\"add\",\"module\":{\"id\":29,\"name\":\"ITP\",\"slug\":\"itp\"}},{\"id\":138,\"name\":\"Update\",\"slug\":\"update\",\"module\":{\"id\":29,\"name\":\"ITP\",\"slug\":\"itp\"}},{\"id\":139,\"name\":\"Delete\",\"slug\":\"delete\",\"module\":{\"id\":29,\"name\":\"ITP\",\"slug\":\"itp\"}},{\"id\":144,\"name\":\"List\",\"slug\":\"list\",\"module\":{\"id\":31,\"name\":\"CommercialQuotation\",\"slug\":\"commercialquotation\"}},{\"id\":145,\"name\":\"Add\",\"slug\":\"add\",\"module\":{\"id\":31,\"name\":\"CommercialQuotation\",\"slug\":\"commercialquotation\"}},{\"id\":146,\"name\":\"Update\",\"slug\":\"update\",\"module\":{\"id\":31,\"name\":\"CommercialQuotation\",\"slug\":\"commercialquotation\"}},{\"id\":147,\"name\":\"Delete\",\"slug\":\"delete\",\"module\":{\"id\":31,\"name\":\"CommercialQuotation\",\"slug\":\"commercialquotation\"}},{\"id\":149,\"name\":\"Evaluation\",\"slug\":\"evaluation\",\"module\":{\"id\":25,\"name\":\"TechnicalQuotation\",\"slug\":\"technicalquotation\"}},{\"id\":150,\"name\":\"View\",\"slug\":\"view\",\"module\":{\"id\":25,\"name\":\"TechnicalQuotation\",\"slug\":\"technicalquotation\"}},{\"id\":151,\"name\":\"Approve\",\"slug\":\"approve\",\"module\":{\"id\":31,\"name\":\"CommercialQuotation\",\"slug\":\"commercialquotation\"}},{\"id\":152,\"name\":\"List\",\"slug\":\"list\",\"module\":{\"id\":32,\"name\":\"MaterialLength\",\"slug\":\"materiallength\"}},{\"id\":153,\"name\":\"Add\",\"slug\":\"add\",\"module\":{\"id\":32,\"name\":\"MaterialLength\",\"slug\":\"materiallength\"}},{\"id\":154,\"name\":\"Update\",\"slug\":\"update\",\"module\":{\"id\":32,\"name\":\"MaterialLength\",\"slug\":\"materiallength\"}},{\"id\":155,\"name\":\"Delete\",\"slug\":\"delete\",\"module\":{\"id\":32,\"name\":\"MaterialLength\",\"slug\":\"materiallength\"}},{\"id\":156,\"name\":\"List\",\"slug\":\"list\",\"module\":{\"id\":33,\"name\":\"WarrantyCondition\",\"slug\":\"warrantycondition\"}},{\"id\":157,\"name\":\"Add\",\"slug\":\"add\",\"module\":{\"id\":33,\"name\":\"WarrantyCondition\",\"slug\":\"warrantycondition\"}},{\"id\":158,\"name\":\"Update\",\"slug\":\"update\",\"module\":{\"id\":33,\"name\":\"WarrantyCondition\",\"slug\":\"warrantycondition\"}},{\"id\":159,\"name\":\"Delete\",\"slug\":\"delete\",\"module\":{\"id\":33,\"name\":\"WarrantyCondition\",\"slug\":\"warrantycondition\"}},{\"id\":160,\"name\":\"List\",\"slug\":\"list\",\"module\":{\"id\":34,\"name\":\"SalesOrder\",\"slug\":\"salesorder\"}},{\"id\":161,\"name\":\"Add\",\"slug\":\"add\",\"module\":{\"id\":34,\"name\":\"SalesOrder\",\"slug\":\"salesorder\"}},{\"id\":162,\"name\":\"Update\",\"slug\":\"update\",\"module\":{\"id\":34,\"name\":\"SalesOrder\",\"slug\":\"salesorder\"}},{\"id\":163,\"name\":\"Delete\",\"slug\":\"delete\",\"module\":{\"id\":34,\"name\":\"SalesOrder\",\"slug\":\"salesorder\"}},{\"id\":164,\"name\":\"HOD Approve\",\"slug\":\"hod_approve\",\"module\":{\"id\":34,\"name\":\"SalesOrder\",\"slug\":\"salesorder\"}},{\"id\":165,\"name\":\"Admin Approve\",\"slug\":\"admin_approve\",\"module\":{\"id\":34,\"name\":\"SalesOrder\",\"slug\":\"salesorder\"}},{\"id\":166,\"name\":\"List\",\"slug\":\"list\",\"module\":{\"id\":35,\"name\":\"Schedule\",\"slug\":\"schedule\"}},{\"id\":167,\"name\":\"Add\",\"slug\":\"add\",\"module\":{\"id\":35,\"name\":\"Schedule\",\"slug\":\"schedule\"}},{\"id\":168,\"name\":\"Update\",\"slug\":\"update\",\"module\":{\"id\":35,\"name\":\"Schedule\",\"slug\":\"schedule\"}},{\"id\":169,\"name\":\"Delete\",\"slug\":\"delete\",\"module\":{\"id\":35,\"name\":\"Schedule\",\"slug\":\"schedule\"}},{\"id\":170,\"name\":\"List\",\"slug\":\"list\",\"module\":{\"id\":36,\"name\":\"FreightBasis\",\"slug\":\"freightbasis\"}},{\"id\":171,\"name\":\"Add\",\"slug\":\"add\",\"module\":{\"id\":36,\"name\":\"FreightBasis\",\"slug\":\"freightbasis\"}},{\"id\":172,\"name\":\"Update\",\"slug\":\"update\",\"module\":{\"id\":36,\"name\":\"FreightBasis\",\"slug\":\"freightbasis\"}},{\"id\":173,\"name\":\"Delete\",\"slug\":\"delete\",\"module\":{\"id\":36,\"name\":\"FreightBasis\",\"slug\":\"freightbasis\"}},{\"id\":174,\"name\":\"Approve\",\"slug\":\"approve\",\"module\":{\"id\":32,\"name\":\"MaterialLength\",\"slug\":\"materiallength\"}},{\"id\":175,\"name\":\"Approve Product\",\"slug\":\"approve-product\",\"module\":{\"id\":6,\"name\":\"Customer\",\"slug\":\"customer\"}},{\"id\":176,\"name\":\"List\",\"slug\":\"list\",\"module\":{\"id\":38,\"name\":\"PurchaseIndent\",\"slug\":\"purchase_indent\"}},{\"id\":177,\"name\":\"Add\",\"slug\":\"add\",\"module\":{\"id\":38,\"name\":\"PurchaseIndent\",\"slug\":\"purchase_indent\"}},{\"id\":178,\"name\":\"Update\",\"slug\":\"update\",\"module\":{\"id\":38,\"name\":\"PurchaseIndent\",\"slug\":\"purchase_indent\"}},{\"id\":179,\"name\":\"Delete\",\"slug\":\"delete\",\"module\":{\"id\":38,\"name\":\"PurchaseIndent\",\"slug\":\"purchase_indent\"}},{\"id\":180,\"name\":\"List\",\"slug\":\"list\",\"module\":{\"id\":39,\"name\":\"PurchaseEnquiry\",\"slug\":\"purchase_enquiry\"}},{\"id\":181,\"name\":\"Add\",\"slug\":\"add\",\"module\":{\"id\":39,\"name\":\"PurchaseEnquiry\",\"slug\":\"purchase_enquiry\"}},{\"id\":182,\"name\":\"Update\",\"slug\":\"update\",\"module\":{\"id\":39,\"name\":\"PurchaseEnquiry\",\"slug\":\"purchase_enquiry\"}},{\"id\":183,\"name\":\"Delete\",\"slug\":\"delete\",\"module\":{\"id\":39,\"name\":\"PurchaseEnquiry\",\"slug\":\"purchase_enquiry\"}},{\"id\":184,\"name\":\"View\",\"slug\":\"view\",\"module\":{\"id\":39,\"name\":\"PurchaseEnquiry\",\"slug\":\"purchase_enquiry\"}},{\"id\":185,\"name\":\"HOD Approve\",\"slug\":\"hod_approve\",\"module\":{\"id\":39,\"name\":\"PurchaseEnquiry\",\"slug\":\"purchase_enquiry\"}},{\"id\":186,\"name\":\"View\",\"slug\":\"view\",\"module\":{\"id\":38,\"name\":\"PurchaseIndent\",\"slug\":\"purchase_indent\"}},{\"id\":187,\"name\":\"List\",\"slug\":\"list\",\"module\":{\"id\":40,\"name\":\"PurchaseOrder\",\"slug\":\"purchase_order\"}},{\"id\":188,\"name\":\"Add\",\"slug\":\"add\",\"module\":{\"id\":40,\"name\":\"PurchaseOrder\",\"slug\":\"purchase_order\"}},{\"id\":189,\"name\":\"Update\",\"slug\":\"update\",\"module\":{\"id\":40,\"name\":\"PurchaseOrder\",\"slug\":\"purchase_order\"}},{\"id\":190,\"name\":\"Delete\",\"slug\":\"delete\",\"module\":{\"id\":40,\"name\":\"PurchaseOrder\",\"slug\":\"purchase_order\"}},{\"id\":191,\"name\":\"View\",\"slug\":\"view\",\"module\":{\"id\":40,\"name\":\"PurchaseOrder\",\"slug\":\"purchase_order\"}},{\"id\":192,\"name\":\"HOD Approve\",\"slug\":\"hod_approve\",\"module\":{\"id\":40,\"name\":\"PurchaseOrder\",\"slug\":\"purchase_order\"}},{\"id\":193,\"name\":\"Management Approve\",\"slug\":\"management_approve\",\"module\":{\"id\":40,\"name\":\"PurchaseOrder\",\"slug\":\"purchase_order\"}},{\"id\":194,\"name\":\"List\",\"slug\":\"list\",\"module\":{\"id\":41,\"name\":\"MRIR\",\"slug\":\"mrir\"}},{\"id\":195,\"name\":\"Add\",\"slug\":\"add\",\"module\":{\"id\":41,\"name\":\"MRIR\",\"slug\":\"mrir\"}},{\"id\":196,\"name\":\"Update\",\"slug\":\"update\",\"module\":{\"id\":41,\"name\":\"MRIR\",\"slug\":\"mrir\"}},{\"id\":197,\"name\":\"Delete\",\"slug\":\"delete\",\"module\":{\"id\":41,\"name\":\"MRIR\",\"slug\":\"mrir\"}},{\"id\":198,\"name\":\"List\",\"slug\":\"list\",\"module\":{\"id\":42,\"name\":\"ChapterHeading\",\"slug\":\"chapter_heading\"}},{\"id\":199,\"name\":\"Add\",\"slug\":\"add\",\"module\":{\"id\":42,\"name\":\"ChapterHeading\",\"slug\":\"chapter_heading\"}},{\"id\":200,\"name\":\"Update\",\"slug\":\"update\",\"module\":{\"id\":42,\"name\":\"ChapterHeading\",\"slug\":\"chapter_heading\"}},{\"id\":201,\"name\":\"Delete\",\"slug\":\"delete\",\"module\":{\"id\":42,\"name\":\"ChapterHeading\",\"slug\":\"chapter_heading\"}},{\"id\":202,\"name\":\"View\",\"slug\":\"view\",\"module\":{\"id\":42,\"name\":\"ChapterHeading\",\"slug\":\"chapter_heading\"}},{\"id\":203,\"name\":\"List\",\"slug\":\"list\",\"module\":{\"id\":43,\"name\":\"Notification\",\"slug\":\"notification\"}},{\"id\":204,\"name\":\"Add\",\"slug\":\"add\",\"module\":{\"id\":43,\"name\":\"Notification\",\"slug\":\"notification\"}},{\"id\":205,\"name\":\"Update\",\"slug\":\"update\",\"module\":{\"id\":43,\"name\":\"Notification\",\"slug\":\"notification\"}},{\"id\":206,\"name\":\"List\",\"slug\":\"list\",\"module\":{\"id\":44,\"name\":\"Pmdc\",\"slug\":\"pmdc_master\"}},{\"id\":207,\"name\":\"Add\",\"slug\":\"add\",\"module\":{\"id\":44,\"name\":\"Pmdc\",\"slug\":\"pmdc_master\"}},{\"id\":208,\"name\":\"Update\",\"slug\":\"update\",\"module\":{\"id\":44,\"name\":\"Pmdc\",\"slug\":\"pmdc_master\"}},{\"id\":209,\"name\":\"Delete\",\"slug\":\"delete\",\"module\":{\"id\":44,\"name\":\"Pmdc\",\"slug\":\"pmdc_master\"}},{\"id\":210,\"name\":\"View\",\"slug\":\"view\",\"module\":{\"id\":44,\"name\":\"Pmdc\",\"slug\":\"pmdc_master\"}},{\"id\":211,\"name\":\"HOD Approve\",\"slug\":\"hod_approve\",\"module\":{\"id\":44,\"name\":\"Pmdc\",\"slug\":\"pmdc_master\"}},{\"id\":212,\"name\":\"Management Approve\",\"slug\":\"management_approve\",\"module\":{\"id\":44,\"name\":\"Pmdc\",\"slug\":\"pmdc_master\"}},{\"id\":213,\"name\":\"List\",\"slug\":\"list\",\"module\":{\"id\":45,\"name\":\"DeliveryOrder\",\"slug\":\"delivery_order\"}},{\"id\":214,\"name\":\"Add\",\"slug\":\"add\",\"module\":{\"id\":45,\"name\":\"DeliveryOrder\",\"slug\":\"delivery_order\"}},{\"id\":215,\"name\":\"Update\",\"slug\":\"update\",\"module\":{\"id\":45,\"name\":\"DeliveryOrder\",\"slug\":\"delivery_order\"}},{\"id\":216,\"name\":\"Delete\",\"slug\":\"delete\",\"module\":{\"id\":45,\"name\":\"DeliveryOrder\",\"slug\":\"delivery_order\"}},{\"id\":217,\"name\":\"View\",\"slug\":\"view\",\"module\":{\"id\":45,\"name\":\"DeliveryOrder\",\"slug\":\"delivery_order\"}},{\"id\":218,\"name\":\"HOD Approve\",\"slug\":\"hod_approve\",\"module\":{\"id\":45,\"name\":\"DeliveryOrder\",\"slug\":\"delivery_order\"}},{\"id\":219,\"name\":\"List\",\"slug\":\"list\",\"module\":{\"id\":46,\"name\":\"StockTransferRequest\",\"slug\":\"stock_transfer_request\"}},{\"id\":220,\"name\":\"Add\",\"slug\":\"add\",\"module\":{\"id\":46,\"name\":\"StockTransferRequest\",\"slug\":\"stock_transfer_request\"}},{\"id\":221,\"name\":\"Update\",\"slug\":\"update\",\"module\":{\"id\":46,\"name\":\"StockTransferRequest\",\"slug\":\"stock_transfer_request\"}},{\"id\":222,\"name\":\"Delete\",\"slug\":\"delete\",\"module\":{\"id\":46,\"name\":\"StockTransferRequest\",\"slug\":\"stock_transfer_request\"}},{\"id\":223,\"name\":\"List\",\"slug\":\"list\",\"module\":{\"id\":47,\"name\":\"StockManagement\",\"slug\":\"stock_management\"}},{\"id\":224,\"name\":\"Delete\",\"slug\":\"delete\",\"module\":{\"id\":47,\"name\":\"StockManagement\",\"slug\":\"stock_management\"}},{\"id\":225,\"name\":\"Approve\",\"slug\":\"approve\",\"module\":{\"id\":47,\"name\":\"StockManagement\",\"slug\":\"stock_management\"}},{\"id\":226,\"name\":\"Add\",\"slug\":\"add\",\"module\":{\"id\":47,\"name\":\"StockManagement\",\"slug\":\"stock_management\"}},{\"id\":227,\"name\":\"List\",\"slug\":\"list\",\"module\":{\"id\":48,\"name\":\"InvoiceMaster\",\"slug\":\"invoice_master\"}},{\"id\":228,\"name\":\"Add\",\"slug\":\"add\",\"module\":{\"id\":48,\"name\":\"InvoiceMaster\",\"slug\":\"invoice_master\"}},{\"id\":229,\"name\":\"Update\",\"slug\":\"update\",\"module\":{\"id\":48,\"name\":\"InvoiceMaster\",\"slug\":\"invoice_master\"}},{\"id\":230,\"name\":\"Delete\",\"slug\":\"delete\",\"module\":{\"id\":48,\"name\":\"InvoiceMaster\",\"slug\":\"invoice_master\"}},{\"id\":231,\"name\":\"View\",\"slug\":\"view\",\"module\":{\"id\":48,\"name\":\"InvoiceMaster\",\"slug\":\"invoice_master\"}},{\"id\":232,\"name\":\"HOD Approve\",\"slug\":\"hod_approve\",\"module\":{\"id\":48,\"name\":\"InvoiceMaster\",\"slug\":\"invoice_master\"}},{\"id\":233,\"name\":\"View\",\"slug\":\"view\",\"module\":{\"id\":46,\"name\":\"StockTransferRequest\",\"slug\":\"stock_transfer_request\"}},{\"id\":234,\"name\":\"HOD Approve\",\"slug\":\"hod_approve\",\"module\":{\"id\":46,\"name\":\"StockTransferRequest\",\"slug\":\"stock_transfer_request\"}},{\"id\":235,\"name\":\"Project Hod\",\"slug\":\"project_hod\",\"module\":{\"id\":25,\"name\":\"TechnicalQuotation\",\"slug\":\"technicalquotation\"}},{\"id\":236,\"name\":\"Non Project Hod\",\"slug\":\"non_project_hod\",\"module\":{\"id\":25,\"name\":\"TechnicalQuotation\",\"slug\":\"technicalquotation\"}},{\"id\":237,\"name\":\"Project Hod\",\"slug\":\"project_hod\",\"module\":{\"id\":31,\"name\":\"CommercialQuotation\",\"slug\":\"commercialquotation\"}},{\"id\":238,\"name\":\"Non Project Hod\",\"slug\":\"non_project_hod\",\"module\":{\"id\":31,\"name\":\"CommercialQuotation\",\"slug\":\"commercialquotation\"}},{\"id\":239,\"name\":\"View\",\"slug\":\"view\",\"module\":{\"id\":34,\"name\":\"SalesOrder\",\"slug\":\"salesorder\"}},{\"id\":245,\"name\":\"List\",\"slug\":\"list\",\"module\":{\"id\":50,\"name\":\"Coating\",\"slug\":\"coating\"}},{\"id\":246,\"name\":\"Add\",\"slug\":\"add\",\"module\":{\"id\":50,\"name\":\"Coating\",\"slug\":\"coating\"}},{\"id\":247,\"name\":\"Update\",\"slug\":\"update\",\"module\":{\"id\":50,\"name\":\"Coating\",\"slug\":\"coating\"}},{\"id\":248,\"name\":\"Delete\",\"slug\":\"delete\",\"module\":{\"id\":50,\"name\":\"Coating\",\"slug\":\"coating\"}},{\"id\":249,\"name\":\"View\",\"slug\":\"view\",\"module\":{\"id\":50,\"name\":\"Coating\",\"slug\":\"coating\"}},{\"id\":250,\"name\":\"List\",\"slug\":\"list\",\"module\":{\"id\":51,\"name\":\"Color\",\"slug\":\"color\"}},{\"id\":251,\"name\":\"Add\",\"slug\":\"add\",\"module\":{\"id\":51,\"name\":\"Color\",\"slug\":\"color\"}},{\"id\":252,\"name\":\"Update\",\"slug\":\"update\",\"module\":{\"id\":51,\"name\":\"Color\",\"slug\":\"color\"}},{\"id\":253,\"name\":\"Delete\",\"slug\":\"delete\",\"module\":{\"id\":51,\"name\":\"Color\",\"slug\":\"color\"}},{\"id\":254,\"name\":\"View\",\"slug\":\"view\",\"module\":{\"id\":51,\"name\":\"Color\",\"slug\":\"color\"}},{\"id\":255,\"name\":\"List\",\"slug\":\"list\",\"module\":{\"id\":52,\"name\":\"Currency\",\"slug\":\"currency\"}},{\"id\":256,\"name\":\"Add\",\"slug\":\"add\",\"module\":{\"id\":52,\"name\":\"Currency\",\"slug\":\"currency\"}},{\"id\":257,\"name\":\"Update\",\"slug\":\"update\",\"module\":{\"id\":52,\"name\":\"Currency\",\"slug\":\"currency\"}},{\"id\":258,\"name\":\"Delete\",\"slug\":\"delete\",\"module\":{\"id\":52,\"name\":\"Currency\",\"slug\":\"currency\"}},{\"id\":259,\"name\":\"View\",\"slug\":\"view\",\"module\":{\"id\":52,\"name\":\"Currency\",\"slug\":\"currency\"}},{\"id\":260,\"name\":\"List\",\"slug\":\"list\",\"module\":{\"id\":53,\"name\":\"EmailTemplate\",\"slug\":\"email_template\"}},{\"id\":261,\"name\":\"Add\",\"slug\":\"add\",\"module\":{\"id\":53,\"name\":\"EmailTemplate\",\"slug\":\"email_template\"}},{\"id\":262,\"name\":\"Update\",\"slug\":\"update\",\"module\":{\"id\":53,\"name\":\"EmailTemplate\",\"slug\":\"email_template\"}},{\"id\":263,\"name\":\"Delete\",\"slug\":\"delete\",\"module\":{\"id\":53,\"name\":\"EmailTemplate\",\"slug\":\"email_template\"}},{\"id\":264,\"name\":\"View\",\"slug\":\"view\",\"module\":{\"id\":53,\"name\":\"EmailTemplate\",\"slug\":\"email_template\"}},{\"id\":265,\"name\":\"List\",\"slug\":\"list\",\"module\":{\"id\":54,\"name\":\"InspectionTestPlan\",\"slug\":\"inspectiontestplan\"}},{\"id\":266,\"name\":\"Add\",\"slug\":\"add\",\"module\":{\"id\":54,\"name\":\"InspectionTestPlan\",\"slug\":\"inspectiontestplan\"}},{\"id\":267,\"name\":\"Update\",\"slug\":\"update\",\"module\":{\"id\":54,\"name\":\"InspectionTestPlan\",\"slug\":\"inspectiontestplan\"}},{\"id\":268,\"name\":\"Delete\",\"slug\":\"delete\",\"module\":{\"id\":54,\"name\":\"InspectionTestPlan\",\"slug\":\"inspectiontestplan\"}},{\"id\":269,\"name\":\"View\",\"slug\":\"view\",\"module\":{\"id\":54,\"name\":\"InspectionTestPlan\",\"slug\":\"inspectiontestplan\"}},{\"id\":270,\"name\":\"List\",\"slug\":\"list\",\"module\":{\"id\":55,\"name\":\"OfferValidityCondition\",\"slug\":\"offervaliditycondition\"}},{\"id\":271,\"name\":\"Add\",\"slug\":\"add\",\"module\":{\"id\":55,\"name\":\"OfferValidityCondition\",\"slug\":\"offervaliditycondition\"}},{\"id\":272,\"name\":\"Update\",\"slug\":\"update\",\"module\":{\"id\":55,\"name\":\"OfferValidityCondition\",\"slug\":\"offervaliditycondition\"}},{\"id\":273,\"name\":\"Delete\",\"slug\":\"delete\",\"module\":{\"id\":55,\"name\":\"OfferValidityCondition\",\"slug\":\"offervaliditycondition\"}},{\"id\":274,\"name\":\"View\",\"slug\":\"view\",\"module\":{\"id\":55,\"name\":\"OfferValidityCondition\",\"slug\":\"offervaliditycondition\"}},{\"id\":275,\"name\":\"List\",\"slug\":\"list\",\"module\":{\"id\":56,\"name\":\"PackingType\",\"slug\":\"packingtype\"}},{\"id\":276,\"name\":\"Add\",\"slug\":\"add\",\"module\":{\"id\":56,\"name\":\"PackingType\",\"slug\":\"packingtype\"}},{\"id\":277,\"name\":\"Update\",\"slug\":\"update\",\"module\":{\"id\":56,\"name\":\"PackingType\",\"slug\":\"packingtype\"}},{\"id\":278,\"name\":\"Delete\",\"slug\":\"delete\",\"module\":{\"id\":56,\"name\":\"PackingType\",\"slug\":\"packingtype\"}},{\"id\":279,\"name\":\"View\",\"slug\":\"view\",\"module\":{\"id\":56,\"name\":\"PackingType\",\"slug\":\"packingtype\"}},{\"id\":280,\"name\":\"List\",\"slug\":\"list\",\"module\":{\"id\":57,\"name\":\"Tax\",\"slug\":\"tax \"}},{\"id\":281,\"name\":\"Add\",\"slug\":\"add\",\"module\":{\"id\":57,\"name\":\"Tax\",\"slug\":\"tax \"}},{\"id\":282,\"name\":\"Update\",\"slug\":\"update\",\"module\":{\"id\":57,\"name\":\"Tax\",\"slug\":\"tax \"}},{\"id\":283,\"name\":\"Delete\",\"slug\":\"delete\",\"module\":{\"id\":57,\"name\":\"Tax\",\"slug\":\"tax \"}},{\"id\":284,\"name\":\"View\",\"slug\":\"view\",\"module\":{\"id\":57,\"name\":\"Tax\",\"slug\":\"tax \"}},{\"id\":290,\"name\":\"List\",\"slug\":\"list\",\"module\":{\"id\":59,\"name\":\"TdsCharge\",\"slug\":\"tdscharge\"}},{\"id\":291,\"name\":\"Add\",\"slug\":\"add\",\"module\":{\"id\":59,\"name\":\"TdsCharge\",\"slug\":\"tdscharge\"}},{\"id\":292,\"name\":\"Update\",\"slug\":\"update\",\"module\":{\"id\":59,\"name\":\"TdsCharge\",\"slug\":\"tdscharge\"}},{\"id\":293,\"name\":\"Delete\",\"slug\":\"delete\",\"module\":{\"id\":59,\"name\":\"TdsCharge\",\"slug\":\"tdscharge\"}},{\"id\":294,\"name\":\"View\",\"slug\":\"view\",\"module\":{\"id\":59,\"name\":\"TdsCharge\",\"slug\":\"tdscharge\"}},{\"id\":295,\"name\":\"List\",\"slug\":\"list\",\"module\":{\"id\":60,\"name\":\"TestCertificate\",\"slug\":\"testcertificate\"}},{\"id\":296,\"name\":\"Add\",\"slug\":\"add\",\"module\":{\"id\":60,\"name\":\"TestCertificate\",\"slug\":\"testcertificate\"}},{\"id\":297,\"name\":\"Update\",\"slug\":\"update\",\"module\":{\"id\":60,\"name\":\"TestCertificate\",\"slug\":\"testcertificate\"}},{\"id\":298,\"name\":\"Delete\",\"slug\":\"delete\",\"module\":{\"id\":60,\"name\":\"TestCertificate\",\"slug\":\"testcertificate\"}},{\"id\":299,\"name\":\"View\",\"slug\":\"view\",\"module\":{\"id\":60,\"name\":\"TestCertificate\",\"slug\":\"testcertificate\"}},{\"id\":300,\"name\":\"List\",\"slug\":\"list\",\"module\":{\"id\":61,\"name\":\"City\",\"slug\":\"city\"}},{\"id\":301,\"name\":\"Add\",\"slug\":\"add\",\"module\":{\"id\":61,\"name\":\"City\",\"slug\":\"city\"}},{\"id\":302,\"name\":\"Update\",\"slug\":\"update\",\"module\":{\"id\":61,\"name\":\"City\",\"slug\":\"city\"}},{\"id\":303,\"name\":\"Delete\",\"slug\":\"delete\",\"module\":{\"id\":61,\"name\":\"City\",\"slug\":\"city\"}},{\"id\":304,\"name\":\"View\",\"slug\":\"view\",\"module\":{\"id\":61,\"name\":\"City\",\"slug\":\"city\"}},{\"id\":305,\"name\":\"List\",\"slug\":\"list\",\"module\":{\"id\":62,\"name\":\"State\",\"slug\":\"state\"}},{\"id\":306,\"name\":\"Add\",\"slug\":\"add\",\"module\":{\"id\":62,\"name\":\"State\",\"slug\":\"state\"}},{\"id\":307,\"name\":\"Update\",\"slug\":\"update\",\"module\":{\"id\":62,\"name\":\"State\",\"slug\":\"state\"}},{\"id\":308,\"name\":\"Delete\",\"slug\":\"delete\",\"module\":{\"id\":62,\"name\":\"State\",\"slug\":\"state\"}},{\"id\":309,\"name\":\"View\",\"slug\":\"view\",\"module\":{\"id\":62,\"name\":\"State\",\"slug\":\"state\"}},{\"id\":310,\"name\":\"List\",\"slug\":\"list\",\"module\":{\"id\":63,\"name\":\"Country\",\"slug\":\"country\"}},{\"id\":311,\"name\":\"Add\",\"slug\":\"add\",\"module\":{\"id\":63,\"name\":\"Country\",\"slug\":\"country\"}},{\"id\":312,\"name\":\"Update\",\"slug\":\"update\",\"module\":{\"id\":63,\"name\":\"Country\",\"slug\":\"country\"}},{\"id\":313,\"name\":\"Delete\",\"slug\":\"delete\",\"module\":{\"id\":63,\"name\":\"Country\",\"slug\":\"country\"}},{\"id\":314,\"name\":\"View\",\"slug\":\"view\",\"module\":{\"id\":63,\"name\":\"Country\",\"slug\":\"country\"}},{\"id\":315,\"name\":\"List\",\"slug\":\"list\",\"module\":{\"id\":64,\"name\":\"VesselMaster\",\"slug\":\"vesselmaster\"}},{\"id\":316,\"name\":\"Add\",\"slug\":\"add\",\"module\":{\"id\":64,\"name\":\"VesselMaster\",\"slug\":\"vesselmaster\"}},{\"id\":317,\"name\":\"Update\",\"slug\":\"update\",\"module\":{\"id\":64,\"name\":\"VesselMaster\",\"slug\":\"vesselmaster\"}},{\"id\":318,\"name\":\"Delete\",\"slug\":\"delete\",\"module\":{\"id\":64,\"name\":\"VesselMaster\",\"slug\":\"vesselmaster\"}},{\"id\":319,\"name\":\"View\",\"slug\":\"view\",\"module\":{\"id\":64,\"name\":\"VesselMaster\",\"slug\":\"vesselmaster\"}},{\"id\":320,\"name\":\"List\",\"slug\":\"list\",\"module\":{\"id\":65,\"name\":\"MaterialProcess\",\"slug\":\"materialprocess\"}},{\"id\":321,\"name\":\"Add\",\"slug\":\"add\",\"module\":{\"id\":65,\"name\":\"MaterialProcess\",\"slug\":\"materialprocess\"}},{\"id\":322,\"name\":\"Update\",\"slug\":\"update\",\"module\":{\"id\":65,\"name\":\"MaterialProcess\",\"slug\":\"materialprocess\"}},{\"id\":323,\"name\":\"Delete\",\"slug\":\"delete\",\"module\":{\"id\":65,\"name\":\"MaterialProcess\",\"slug\":\"materialprocess\"}},{\"id\":324,\"name\":\"View\",\"slug\":\"view\",\"module\":{\"id\":65,\"name\":\"MaterialProcess\",\"slug\":\"materialprocess\"}},{\"id\":325,\"name\":\"List\",\"slug\":\"list\",\"module\":{\"id\":66,\"name\":\"MaterialGroup\",\"slug\":\"materialgroup\"}},{\"id\":326,\"name\":\"Add\",\"slug\":\"add\",\"module\":{\"id\":66,\"name\":\"MaterialGroup\",\"slug\":\"materialgroup\"}},{\"id\":327,\"name\":\"Update\",\"slug\":\"update\",\"module\":{\"id\":66,\"name\":\"MaterialGroup\",\"slug\":\"materialgroup\"}},{\"id\":328,\"name\":\"Delete\",\"slug\":\"delete\",\"module\":{\"id\":66,\"name\":\"MaterialGroup\",\"slug\":\"materialgroup\"}},{\"id\":329,\"name\":\"View\",\"slug\":\"view\",\"module\":{\"id\":66,\"name\":\"MaterialGroup\",\"slug\":\"materialgroup\"}},{\"id\":330,\"name\":\"View\",\"slug\":\"view\",\"module\":{\"id\":67,\"name\":\"Dashboard\",\"slug\":\"dashboard\"}},{\"id\":331,\"name\":\"List\",\"slug\":\"list\",\"module\":{\"id\":68,\"name\":\"TaxAddonCharges\",\"slug\":\"taxaddoncharges\"}},{\"id\":332,\"name\":\"Add\",\"slug\":\"add\",\"module\":{\"id\":68,\"name\":\"TaxAddonCharges\",\"slug\":\"taxaddoncharges\"}},{\"id\":333,\"name\":\"Update\",\"slug\":\"update\",\"module\":{\"id\":68,\"name\":\"TaxAddonCharges\",\"slug\":\"taxaddoncharges\"}},{\"id\":334,\"name\":\"Delete\",\"slug\":\"delete\",\"module\":{\"id\":68,\"name\":\"TaxAddonCharges\",\"slug\":\"taxaddoncharges\"}},{\"id\":335,\"name\":\"View\",\"slug\":\"view\",\"module\":{\"id\":68,\"name\":\"TaxAddonCharges\",\"slug\":\"taxaddoncharges\"}},{\"id\":336,\"name\":\"EFR\",\"slug\":\"efr\",\"module\":{\"id\":25,\"name\":\"TechnicalQuotation\",\"slug\":\"technicalquotation\"}},{\"id\":337,\"name\":\"List\",\"slug\":\"list\",\"module\":{\"id\":69,\"name\":\"PurchaseOrderRejected\",\"slug\":\"purchase_order_rejected\"}},{\"id\":338,\"name\":\"Add\",\"slug\":\"add\",\"module\":{\"id\":69,\"name\":\"PurchaseOrderRejected\",\"slug\":\"purchase_order_rejected\"}},{\"id\":339,\"name\":\"Update\",\"slug\":\"update\",\"module\":{\"id\":69,\"name\":\"PurchaseOrderRejected\",\"slug\":\"purchase_order_rejected\"}},{\"id\":340,\"name\":\"Delete\",\"slug\":\"delete\",\"module\":{\"id\":69,\"name\":\"PurchaseOrderRejected\",\"slug\":\"purchase_order_rejected\"}},{\"id\":341,\"name\":\"View\",\"slug\":\"view\",\"module\":{\"id\":69,\"name\":\"PurchaseOrderRejected\",\"slug\":\"purchase_order_rejected\"}},{\"id\":342,\"name\":\"HOD Approve\",\"slug\":\"hod_approve\",\"module\":{\"id\":69,\"name\":\"PurchaseOrderRejected\",\"slug\":\"purchase_order_rejected\"}},{\"id\":343,\"name\":\"List\",\"slug\":\"list\",\"module\":{\"id\":70,\"name\":\"Exchange Rate\",\"slug\":\"exchange_rate\"}},{\"id\":344,\"name\":\"Add\",\"slug\":\"add\",\"module\":{\"id\":70,\"name\":\"Exchange Rate\",\"slug\":\"exchange_rate\"}},{\"id\":345,\"name\":\"Update\",\"slug\":\"update\",\"module\":{\"id\":70,\"name\":\"Exchange Rate\",\"slug\":\"exchange_rate\"}},{\"id\":346,\"name\":\"Delete\",\"slug\":\"delete\",\"module\":{\"id\":70,\"name\":\"Exchange Rate\",\"slug\":\"exchange_rate\"}},{\"id\":347,\"name\":\"View\",\"slug\":\"view\",\"module\":{\"id\":70,\"name\":\"Exchange Rate\",\"slug\":\"exchange_rate\"}},{\"id\":348,\"name\":\"List\",\"slug\":\"list\",\"module\":{\"id\":71,\"name\":\"Audit Log\",\"slug\":\"auditlog\"}},{\"id\":349,\"name\":\"Delete\",\"slug\":\"delete\",\"module\":{\"id\":71,\"name\":\"Audit Log\",\"slug\":\"auditlog\"}},{\"id\":350,\"name\":\"View\",\"slug\":\"view\",\"module\":{\"id\":72,\"name\":\"Report\",\"slug\":\"report\"}},{\"id\":351,\"name\":\"Export\",\"slug\":\"export\",\"module\":{\"id\":72,\"name\":\"Report\",\"slug\":\"report\"}},{\"id\":352,\"name\":\"Approve\",\"slug\":\"approve\",\"module\":{\"id\":22,\"name\":\"Dimension\",\"slug\":\"dimension\"}},{\"id\":353,\"name\":\"Approve\",\"slug\":\"approve\",\"module\":{\"id\":35,\"name\":\"Schedule\",\"slug\":\"schedule\"}},{\"id\":354,\"name\":\"From Excel\",\"slug\":\"from_excel\",\"module\":{\"id\":23,\"name\":\"Product\",\"slug\":\"product\"}},{\"id\":355,\"name\":\"From Excel\",\"slug\":\"from_excel\",\"module\":{\"id\":22,\"name\":\"Dimension\",\"slug\":\"dimension\"}},{\"id\":356,\"name\":\"From Excel\",\"slug\":\"from_excel\",\"module\":{\"id\":35,\"name\":\"Schedule\",\"slug\":\"schedule\"}},{\"id\":357,\"name\":\"Approve\",\"slug\":\"approve\",\"module\":{\"id\":66,\"name\":\"MaterialGroup\",\"slug\":\"materialgroup\"}},{\"id\":358,\"name\":\"List\",\"slug\":\"list\",\"module\":{\"id\":73,\"name\":\"Document\",\"slug\":\"document\"}},{\"id\":359,\"name\":\"Add\",\"slug\":\"add\",\"module\":{\"id\":73,\"name\":\"Document\",\"slug\":\"document\"}},{\"id\":360,\"name\":\"Update\",\"slug\":\"update\",\"module\":{\"id\":73,\"name\":\"Document\",\"slug\":\"document\"}},{\"id\":361,\"name\":\"Delete\",\"slug\":\"delete\",\"module\":{\"id\":73,\"name\":\"Document\",\"slug\":\"document\"}},{\"id\":362,\"name\":\"View Address\",\"slug\":\"view_address\",\"module\":{\"id\":6,\"name\":\"Customer\",\"slug\":\"customer\"}},{\"id\":363,\"name\":\"Move Department\",\"slug\":\"move_department\",\"module\":{\"id\":25,\"name\":\"TechnicalQuotation\",\"slug\":\"technicalquotation\"}},{\"id\":364,\"name\":\"Reverse SO\",\"slug\":\"reverse_so\",\"module\":{\"id\":34,\"name\":\"SalesOrder\",\"slug\":\"salesorder\"}},{\"id\":365,\"name\":\"Price Enable\",\"slug\":\"price_enable\",\"module\":{\"id\":25,\"name\":\"TechnicalQuotation\",\"slug\":\"technicalquotation\"}},{\"id\":366,\"name\":\"List\",\"slug\":\"list\",\"module\":{\"id\":74,\"name\":\"Dashboard Filters\",\"slug\":\"flag\"}},{\"id\":367,\"name\":\"Add\",\"slug\":\"add\",\"module\":{\"id\":74,\"name\":\"Dashboard Filters\",\"slug\":\"flag\"}},{\"id\":368,\"name\":\"Update\",\"slug\":\"update\",\"module\":{\"id\":74,\"name\":\"Dashboard Filters\",\"slug\":\"flag\"}},{\"id\":369,\"name\":\"Delete\",\"slug\":\"delete\",\"module\":{\"id\":74,\"name\":\"Dashboard Filters\",\"slug\":\"flag\"}},{\"id\":370,\"name\":\"Project List\",\"slug\":\"project\",\"module\":{\"id\":25,\"name\":\"TechnicalQuotation\",\"slug\":\"technicalquotation\"}},{\"id\":371,\"name\":\"OEM List\",\"slug\":\"oem\",\"module\":{\"id\":25,\"name\":\"TechnicalQuotation\",\"slug\":\"technicalquotation\"}},{\"id\":372,\"name\":\"Retail List\",\"slug\":\"retail\",\"module\":{\"id\":25,\"name\":\"TechnicalQuotation\",\"slug\":\"technicalquotation\"}},{\"id\":373,\"name\":\"List\",\"slug\":\"list\",\"module\":{\"id\":75,\"name\":\"TaxMaster\",\"slug\":\"taxmaster\"}},{\"id\":374,\"name\":\"Add\",\"slug\":\"add\",\"module\":{\"id\":75,\"name\":\"TaxMaster\",\"slug\":\"taxmaster\"}},{\"id\":375,\"name\":\"Update\",\"slug\":\"update\",\"module\":{\"id\":75,\"name\":\"TaxMaster\",\"slug\":\"taxmaster\"}},{\"id\":376,\"name\":\"Delete\",\"slug\":\"delete\",\"module\":{\"id\":75,\"name\":\"TaxMaster\",\"slug\":\"taxmaster\"}},{\"id\":377,\"name\":\"List\",\"slug\":\"list\",\"module\":{\"id\":76,\"name\":\"TaxProfile\",\"slug\":\"taxprofile\"}},{\"id\":378,\"name\":\"Add\",\"slug\":\"add\",\"module\":{\"id\":76,\"name\":\"TaxProfile\",\"slug\":\"taxprofile\"}},{\"id\":379,\"name\":\"Update\",\"slug\":\"update\",\"module\":{\"id\":76,\"name\":\"TaxProfile\",\"slug\":\"taxprofile\"}},{\"id\":380,\"name\":\"Delete\",\"slug\":\"delete\",\"module\":{\"id\":76,\"name\":\"TaxProfile\",\"slug\":\"taxprofile\"}},{\"id\":381,\"name\":\"Add\",\"slug\":\"add\",\"module\":{\"id\":77,\"name\":\"TaxGroup\",\"slug\":\"taxgroup\"}},{\"id\":382,\"name\":\"List\",\"slug\":\"list\",\"module\":{\"id\":78,\"name\":\"SupplierPaymentTerms\",\"slug\":\"supplier_payment_terms_master\"}},{\"id\":383,\"name\":\"Add\",\"slug\":\"add\",\"module\":{\"id\":78,\"name\":\"SupplierPaymentTerms\",\"slug\":\"supplier_payment_terms_master\"}},{\"id\":384,\"name\":\"Update\",\"slug\":\"update\",\"module\":{\"id\":78,\"name\":\"SupplierPaymentTerms\",\"slug\":\"supplier_payment_terms_master\"}},{\"id\":385,\"name\":\"Delete\",\"slug\":\"delete\",\"module\":{\"id\":78,\"name\":\"SupplierPaymentTerms\",\"slug\":\"supplier_payment_terms_master\"}},{\"id\":386,\"name\":\"List\",\"slug\":\"list\",\"module\":{\"id\":79,\"name\":\"SupplierDeliveryConditions\",\"slug\":\"supplier_delivery_conditions_master\"}},{\"id\":387,\"name\":\"Add\",\"slug\":\"add\",\"module\":{\"id\":79,\"name\":\"SupplierDeliveryConditions\",\"slug\":\"supplier_delivery_conditions_master\"}},{\"id\":388,\"name\":\"Update\",\"slug\":\"update\",\"module\":{\"id\":79,\"name\":\"SupplierDeliveryConditions\",\"slug\":\"supplier_delivery_conditions_master\"}},{\"id\":389,\"name\":\"Delete\",\"slug\":\"delete\",\"module\":{\"id\":79,\"name\":\"SupplierDeliveryConditions\",\"slug\":\"supplier_delivery_conditions_master\"}},{\"id\":390,\"name\":\"List\",\"slug\":\"list\",\"module\":{\"id\":80,\"name\":\"SupplierDeliveryLocation\",\"slug\":\"supplier_delivery_location_master\"}},{\"id\":391,\"name\":\"Add\",\"slug\":\"add\",\"module\":{\"id\":80,\"name\":\"SupplierDeliveryLocation\",\"slug\":\"supplier_delivery_location_master\"}},{\"id\":392,\"name\":\"Update\",\"slug\":\"update\",\"module\":{\"id\":80,\"name\":\"SupplierDeliveryLocation\",\"slug\":\"supplier_delivery_location_master\"}},{\"id\":393,\"name\":\"Delete\",\"slug\":\"delete\",\"module\":{\"id\":80,\"name\":\"SupplierDeliveryLocation\",\"slug\":\"supplier_delivery_location_master\"}},{\"id\":394,\"name\":\"Revise Quotation\",\"slug\":\"revise_quotation\",\"module\":{\"id\":31,\"name\":\"CommercialQuotation\",\"slug\":\"commercialquotation\"}},{\"id\":399,\"name\":\"List\",\"slug\":\"list\",\"module\":{\"id\":82,\"name\":\"InspectionActivityProfile\",\"slug\":\"inspection_activity_profile_master\"}},{\"id\":400,\"name\":\"Add\",\"slug\":\"add\",\"module\":{\"id\":82,\"name\":\"InspectionActivityProfile\",\"slug\":\"inspection_activity_profile_master\"}},{\"id\":401,\"name\":\"Update\",\"slug\":\"update\",\"module\":{\"id\":82,\"name\":\"InspectionActivityProfile\",\"slug\":\"inspection_activity_profile_master\"}},{\"id\":403,\"name\":\"List\",\"slug\":\"list\",\"module\":{\"id\":83,\"name\":\"QuotationCloseReason\",\"slug\":\"quotation_close_reason_master\"}},{\"id\":404,\"name\":\"Add\",\"slug\":\"add\",\"module\":{\"id\":83,\"name\":\"QuotationCloseReason\",\"slug\":\"quotation_close_reason_master\"}},{\"id\":405,\"name\":\"Update\",\"slug\":\"update\",\"module\":{\"id\":83,\"name\":\"QuotationCloseReason\",\"slug\":\"quotation_close_reason_master\"}},{\"id\":406,\"name\":\"Delete\",\"slug\":\"delete\",\"module\":{\"id\":83,\"name\":\"QuotationCloseReason\",\"slug\":\"quotation_close_reason_master\"}},{\"id\":407,\"name\":\"Project List\",\"slug\":\"project\",\"module\":{\"id\":6,\"name\":\"Customer\",\"slug\":\"customer\"}},{\"id\":408,\"name\":\"OEM List\",\"slug\":\"oem\",\"module\":{\"id\":6,\"name\":\"Customer\",\"slug\":\"customer\"}},{\"id\":409,\"name\":\"Retail List\",\"slug\":\"retail\",\"module\":{\"id\":6,\"name\":\"Customer\",\"slug\":\"customer\"}},{\"id\":410,\"name\":\"Expense Reimbursement Status\",\"slug\":\"expense_status\",\"module\":{\"id\":84,\"name\":\"VisitSummary\",\"slug\":\"visit_summary\"}},{\"id\":413,\"name\":\"Purchase Status Update\",\"slug\":\"purchase_status\",\"module\":{\"id\":25,\"name\":\"TechnicalQuotation\",\"slug\":\"technicalquotation\"}},{\"id\":415,\"name\":\"Add\",\"slug\":\"add\",\"module\":{\"id\":85,\"name\":\"Supplier Price List\",\"slug\":\"supplier_price_list\"}},{\"id\":418,\"name\":\"Estimation Date Bulk Update\",\"slug\":\"po_estimation_date_b\",\"module\":{\"id\":40,\"name\":\"PurchaseOrder\",\"slug\":\"purchase_order\"}},{\"id\":419,\"name\":\"List\",\"slug\":\"list\",\"module\":{\"id\":86,\"name\":\"Currency\",\"slug\":\"currency_master\"}},{\"id\":420,\"name\":\"Add\",\"slug\":\"add\",\"module\":{\"id\":86,\"name\":\"Currency\",\"slug\":\"currency_master\"}},{\"id\":421,\"name\":\"Update\",\"slug\":\"update\",\"module\":{\"id\":86,\"name\":\"Currency\",\"slug\":\"currency_master\"}},{\"id\":422,\"name\":\"Delete\",\"slug\":\"delete\",\"module\":{\"id\":86,\"name\":\"Currency\",\"slug\":\"currency_master\"}},{\"id\":423,\"name\":\"List\",\"slug\":\"list\",\"module\":{\"id\":87,\"name\":\"Historical Currency\",\"slug\":\"historical_currency_master\"}},{\"id\":424,\"name\":\"Add\",\"slug\":\"add\",\"module\":{\"id\":87,\"name\":\"Historical Currency\",\"slug\":\"historical_currency_master\"}},{\"id\":425,\"name\":\"Update\",\"slug\":\"update\",\"module\":{\"id\":87,\"name\":\"Historical Currency\",\"slug\":\"historical_currency_master\"}},{\"id\":426,\"name\":\"Delete\",\"slug\":\"delete\",\"module\":{\"id\":87,\"name\":\"Historical Currency\",\"slug\":\"historical_currency_master\"}},{\"id\":429,\"name\":\"Update\",\"slug\":\"update\",\"module\":{\"id\":88,\"name\":\"Versioning\",\"slug\":\"versioning_module\"}}]}"
        },
        {
          "name": "branch",
          "value": "{\"id\":3,\"name\":\"BANGALORE\"}"
        },
        {
          "name": "gleap-widget-config-MUYkFaomRZDFwKtzWCO8WH2DIYLQKObz-en-us",
          "value": "{\"flowConfig\":{\"newsMenuLabel\":\"News\",\"checklistMenuLabel\":\"Tasks\",\"featureRequestsMenuLabel\":\"Roadmap\",\"allConversationsMenuLabel\":\"Messages\",\"knowledgeBaseMenuLabel\":\"Help\",\"welcomeText\":\"How can we help you today?\",\"replyTime\":\"We usually reply within a few minutes\",\"color\":\"#007a5c\",\"bgType\":\"classic\",\"animateBG\":false,\"vision\":true,\"bgBlur\":false,\"backgroundColor\":\"#ffffff\",\"headerColor\":\"#007a5c\",\"headerColor2\":\"#007a5c\",\"headerColor3\":\"#75D2DA\",\"buttonColor\":\"#007a5c\",\"borderRadius\":21,\"buttonX\":\"60\",\"buttonY\":\"10\",\"operatorAvatarImage\":\"\",\"operatorName\":\"Kai\",\"logo\":\"https://staticfiles.gleap.io/gfeedback_widgets/4CQiEldZzcDbFFsgVmXTnY9FnGP5SjMnwot1D9LGfpkEObv3ushDDH4H0tsRBL2Sw1W5GuR9oDy.svg\",\"buttonLogo\":\"\",\"customCSS\":\"\",\"hideFeatureRequests\":false,\"hideNews\":false,\"hideAllConversations\":false,\"hideKnowledgeBase\":true,\"openingTimes\":[{\"day\":\"Weekdays\",\"openingTime\":\"09:00\",\"closingTime\":\"17:00\"}],\"timezone\":\"Asia/Kolkata\",\"showOnlineStatus\":true,\"spamProtection\":false,\"hideBranding\":true,\"enableConsoleLogs\":true,\"showHomeHelpCenter\":true,\"enableReplays\":false,\"enableWebReplays\":true,\"hideForGuests\":false,\"replaysInterval\":5,\"thankYouDuration\":3000,\"enableNetworkLogs\":true,\"sendNetworkResources\":false,\"networkLogPropsToIgnore\":[],\"networkLogBlacklist\":[],\"enablePrivacyPolicy\":false,\"enableShortcuts\":false,\"privacyPolicyURL\":\"\",\"enableMenu\":true,\"menuItems\":[{\"title\":\"Report an issue\",\"description\":\"Found a bug? Let us know.\",\"icon\":\"https://gleapcdn.com/res/iconbug.svg\",\"actionType\":\"bugreporting\",\"color\":\"#F4CAC8\"},{\"title\":\"Request a feature\",\"description\":\"What would you like to see next?\",\"icon\":\"https://gleapcdn.com/res/iconidea.svg\",\"actionType\":\"featurerequests\",\"color\":\"#FFEEC2\"},{\"title\":\"Send us a message\",\"description\":\"We are here to help.\",\"icon\":\"https://gleapcdn.com/res/iconcontact.svg\",\"actionType\":\"BOT\",\"color\":\"#EFE2FF\"}],\"activationMethodFeedbackButton\":true,\"activationMethodShake\":false,\"activationMethodScreenshotGesture\":false,\"enableCrashDetector\":false,\"crashDetectorIsSilent\":false,\"enableRageClickDetector\":false,\"rageClickDetectorIsSilent\":false,\"enableNetworkLogFilters\":false,\"jsMajorVersion\":\"v6\",\"enableIntercomCompatibilityMode\":true,\"hideWavingHandAfterName\":false,\"hideUsersName\":false,\"hideTeam\":false,\"widgetButtonText\":\"Feedback\",\"showInfoPopup\":false,\"feedbackButtonPosition\":\"BUTTON_CLASSIC\",\"helpcenterConfig\":{\"kaiAnswers\":true,\"localization\":[{\"language\":\"en\",\"title\":\"Help center\",\"description\":\"Find answers to your questions\"}],\"config\":{\"logoUrl\":\"\"}},\"staticTranslations\":{\"scheduled\":\" Scheduled\",\"done\":\"Done\",\"open\":\"Open\",\"Reply\":\"Reply\",\"next\":\"Next\",\"previous\":\"Previous\",\"unmuteModalTitle\":\"This tour contains audio. Do you want to unmute?\",\"unmuteModalButton\":\"Yes, unmute\",\"unmuteModalContinue\":\"Continue without audio\",\"invalidNumberMessage\":\"Please reply with a valid number.\",\"unsupportedInputType\":\"This input type is not supported.\",\"invalidEmailMessage\":\"Please reply with a valid email address.\",\"plainTextRatingMessage\":\"Kindly reply with a number on a scale of 1 (poor quality) to 5 (excellent).\",\"unsubscribeFromEmails\":\"Unsubscribe from these emails\",\"wrongApiKey\":\"Wrong API key\",\"kaiJoinedSession\":\"has joined the session\",\"kaiGatheringInformation\":\"Gathering information...\",\"kaiThinking\":\"Thinking...\",\"kaiListening\":\"Listening...\",\"kaiReportABug\":\"Report a bug\",\"kaiIssue\":\"Unfortunately, I'm not able to answer your question at the moment.\",\"kaiAnswerTag\":\"Answer\",\"kaiSources\":\"Source\",\"kaiSubmitIdea\":\"Submit my idea\",\"kaiSubmitIdeaDone\":\"Back to Home\",\"featureRequestSort\":\"Most votes\",\"featureRequestSortDate\":\"Recent\",\"featureRequestStatus\":\"Status\",\"featureRequestTags\":\"Tags\",\"nothingFoundTitle\":\"Nothing found\",\"nothingFoundDescription\":\"Try to reset the filters to see more feature requests.\",\"nothingUnseenTitle\":\"Nothing unread, good job \",\"nothingUnseenDescription\":\"There are no unread feature requests waiting for you.\",\"noFeatureRequestsTitle\":\"No feature requests yet\",\"noFeatureRequestsDescription\":\"New feature requests will show up, as soon as they get reported.\",\"resetFiltersOr\":\"Try to reset the filters or\",\"submitNewFeatureRequrest\":\"submit a new feature request\",\"email\":\"E-mail\",\"yourEmail\":\"Your e-mail\",\"markTheBug\":\"Mark the bug\",\"recordScreen\":\"Record screen\",\"clickAndDragToMarkTheBug\":\"Click and drag to mark the bug\",\"retry\":\"Retry\",\"mute\":\"Mute\",\"unmute\":\"Unmute\",\"browserNotSupported\":\"Browser not supported\",\"stopRecording\":\"Stop recording\",\"startRecording\":\"Start recording\",\"pickAColor\":\"Pick a color\",\"taskProgress\":\"{a} of {b} done\",\"aboutMinutes\":\"About {a} minutes left\",\"markAsDone\":\"Mark as done\",\"nextStep\":\"Next step\",\"undo\":\"Undo\",\"drawOnTheScreenToMarkTheBug\":\"Draw on the screen to mark the bug\",\"recordYourScreenToShowcaseTheBug\":\"Record your screen to showcase the bug\",\"writeReply\":\"Write a reply...\",\"recording\":\"Recording...\",\"chooseOption\":\"Choose one...\",\"chooseBotOption\":\"Please choose an option below.\",\"screenRecording\":\"Screen recording\",\"screenshot\":\"Screenshot\",\"within a few minutes\":\"within a few minutes\",\"within a few hours\":\"within a few hours\",\"within a day\":\"within a day\",\"weAreOffline\":\"We are currently offline but will get back to you as soon as possible.\",\"weAreBack\":\"We are back\",\"ppolicyIRead\":\"I read and accept the \",\"ppolicy\":\"privacy policy\",\"noMessages\":\"No messages yet\",\"submit\":\"Submit\",\"homeLabel\":\"Home\",\"chooseFile\":\"Choose a file or drag it here.\",\"hi\":\"Hi\",\"sendMessage\":\"Send us a message\",\"noChecklists\":\"You completed all tasks.\",\"noNews\":\"No news published yet.\",\"loadMore\":\"Load more\",\"suggestFeatureRequest\":\"We found existing feature requests that might align with your idea. Upvote the ones you like or go ahead and submit your own idea.\",\"conversationEnded\":\"Your conversation has ended.\",\"wrongConversationChannel\":\"To continue this conversation, please switch to {channel}.\",\"featureRequestShow\":\"Show\",\"composerGreeting\":\"Hey\",\"featureRequestSortRandom\":\"Random\",\"requestFeature\":\"Request a feature\",\"search\":\"Search...\",\"botReplyTime\":\"Our bot will reply instantly\",\"submitted\":\"Submitted\",\"inProgress\":\"In progress\",\"resolved\":\"Resolved\",\"noAnswer\":\"No answer found.\",\"featureRequests\":\"Feature requests\",\"roadmap\":\"Roadmap\",\"news\":\"News\",\"notDone\":\"Not done\",\"released\":\"Released\",\"all\":\"All\",\"comments\":\"Comments\",\"updates\":\"Updates\",\"writeComment\":\"Write a comment\",\"writeCommentPlaceholder\":\"Write a comment...\",\"send\":\"Send\",\"noComments\":\"No comments yet\",\"noUpdates\":\"No updates yet\",\"kickstartTheConversation\":\"Kickstart the conversation by writing a comment.\",\"weWillPostUpdates\":\"We will post updates on this feature request here.\",\"conversationHistoryMailMessage\":\"Hey there, weve attached the history of your last conversation.\"},\"fadebg\":true,\"stn\":true,\"sts\":true,\"stt\":true,\"visibleTeamMembers\":[\"64a50bcb812dfc547f25b7a1\",\"6759dc98e1a7594811091396\",\"6757d7071f07684d560b41be\"],\"name\":\"Evergreen ERP\",\"localizationOptions\":{\"language\":\"en\",\"rtl\":false}},\"projectActions\":{}}"
        },
        {
          "name": "gleap-widget-session-MUYkFaomRZDFwKtzWCO8WH2DIYLQKObz",
          "value": "{\"gleapId\":\"0d034fa7-22b8-4df6-b9e9-4baecd862aeb\",\"gleapHash\":\"6ea0523cbe0d3a73adbb8314b0095e45bc6a1c66cbb59cc2087ed5dcf5c39261\",\"value\":0,\"lang\":\"en-us\",\"id\":\"68396fe20788db58ea8b1fae\"}"
        }
      ]
    }
  ]
}